{
  "id": "machining-time-explained",
  "title": "Machining Time Explained - AluCalc Engineering",
  "slug": "machining-time-explained",
  "keyword": "machining time explained",
  "intent": "explained",
  "meta": {
    "title": "Machining Time Explained | Free Engineering Tool | AluCalc",
    "description": "Professional machining time explained tool. Real formulas, worked examples, and step-by-step engineering explanations."
  },
  "seo": {
    "h1": "Machining Time Explained",
    "intro": "Comprehensive engineering guide for machining time explained. Use this resource to determine specifications, validate designs, and review standards.",
    "formula": "(Placeholder formula for machining time)",
    "variables": {
      "var1": "Input parameter 1",
      "var2": "Input parameter 2"
    },
    "step_by_step": "1. Identify inputs for machining time.\n2. Apply the governing equation.\n3. Validate against engineering standards.",
    "practical": "Machining Time is critical in real-world engineering for system reliability and safety.",
    "example": "Example: For a typical machining time scenario, substituting standard values yields a result within acceptable limits."
  },
  "related": [
    "cnc-speed-calculator",
    "cnc-feed-rate-calculator",
    "cutting-speed-calculator",
    "tool-life-calculator",
    "machining-time-formula"
  ],
  "cta": {
    "label": "Open in AluCalc OS",
    "link": "/os?module=calculator"
  }
}