{
  "id": "poisson-ratio-calculator",
  "title": "Poisson Ratio Calculator - AluCalc Engineering",
  "slug": "poisson-ratio-calculator",
  "keyword": "poisson ratio calculator",
  "intent": "calculator",
  "meta": {
    "title": "Poisson Ratio Calculator | Free Engineering Tool | AluCalc",
    "description": "Professional poisson ratio calculator tool. Real formulas, worked examples, and step-by-step engineering explanations."
  },
  "seo": {
    "h1": "Poisson Ratio Calculator",
    "intro": "Comprehensive engineering guide for poisson ratio calculator. Use this resource to determine specifications, validate designs, and review standards.",
    "formula": "(Placeholder formula for poisson ratio)",
    "variables": {
      "var1": "Input parameter 1",
      "var2": "Input parameter 2"
    },
    "step_by_step": "1. Identify inputs for poisson ratio.\n2. Apply the governing equation.\n3. Validate against engineering standards.",
    "practical": "Poisson Ratio is critical in real-world engineering for system reliability and safety.",
    "example": "Example: For a typical poisson ratio scenario, substituting standard values yields a result within acceptable limits."
  },
  "related": [
    "stress-strain-calculator",
    "young-modulus-calculator",
    "shear-modulus-calculator",
    "yield-strength-calculator",
    "poisson-ratio-formula"
  ],
  "cta": {
    "label": "Open in AluCalc OS",
    "link": "/os?module=calculator"
  }
}